scrapecraft/__init__.py
scrapecraft/dispatch.py
scrapecraft/dispatch_helpers.py
scrapecraft/download.py
scrapecraft/download_helpers.py
scrapecraft/extract.py
scrapecraft/extract_helpers.py
scrapecraft/scraper.py
scrapecraft/utils.py
scrapecraft-0.1.0a0.dev0.dist-info/METADATA
scrapecraft-0.1.0a0.dev0.dist-info/WHEEL
scrapecraft-0.1.0a0.dev0.dist-info/top_level.txt
scrapecraft-0.1.0a0.dev0.dist-info/RECORD
