Metadata-Version: 2.4
Name: scrapecraft
Version: 0.1.0a0.dev0
Summary: Add your description here
Requires-Python: >=3.12
Requires-Dist: blinker>=1.9.0
Requires-Dist: pydantic-settings>=2.9.1
Requires-Dist: pydantic>=2.11.3
Requires-Dist: requests>=2.32.3
Requires-Dist: python-ulid>=3.0.0
Requires-Dist: smart-open>=7.1.0
Requires-Dist: parsel>=1.10.0
Requires-Dist: svgwrite>=1.4.3
